byroapi/__init__.py
byroapi/base.py
byroapi/byroapi.py
byroapi/cli.py
byroapi/default_config.yaml
byroapi/http_handler.py
byroapi/template.py
byroapi-0.2.1.dist-info/entry_points.txt
byroapi-0.2.1.dist-info/LICENSE
byroapi-0.2.1.dist-info/WHEEL
byroapi-0.2.1.dist-info/METADATA
byroapi-0.2.1.dist-info/RECORD
