Metadata-Version: 2.1
Name: byroapi
Version: 0.2.1
Summary: REST API service for filling in and signig forms.
Home-page: https://github.com/JNevrly/byroapi
License: MIT
Author: Josef Nevrly
Author-email: josef.nevrly@gmail.com
Requires-Python: >=3.8.0,<4.0.0
Classifier: Development Status :: 2 - Pre-Alpha
Classifier: Intended Audience :: Developers
Classifier: License :: OSI Approved :: MIT License
Classifier: Natural Language :: English
Classifier: Programming Language :: Python :: 3
Classifier: Programming Language :: Python :: 3.10
Classifier: Programming Language :: Python :: 3.7
Classifier: Programming Language :: Python :: 3.8
Classifier: Programming Language :: Python :: 3.9
Requires-Dist: PyPDF2 (>=1.26.0,<2.0.0)
Requires-Dist: PyYAML (>=6.0,<7.0)
Requires-Dist: aiohttp (>=3.7.4,<4.0.0)
Requires-Dist: aioyagmail (>=0.0.4,<0.0.5)
Requires-Dist: click (>=8.0.1,<9.0.0)
Requires-Dist: onacol (>=0.3.0,<0.4.0)
Requires-Dist: reportlab (>=3.6.5,<4.0.0)
Project-URL: Documentation, https://github.com/JNevrly/byroapi
Project-URL: Repository, https://github.com/JNevrly/byroapi
